{
  "__type__": "cc.JsonAsset",
  "_name": "guildtaskConfig",
  "json": {
    "1001": {
      "type": 1,
      "condition": 75,
      "name": "扫荡怪物",
      "text": "前方兵马遭到强力怪物，请前往支援",
      "desc": "扫荡怪物中",
      "doc": "扫荡已完成",
      "ress": {
        "10": 10
      },
      "weight": 1000,
      "time": 4
    },
    "1002": {
      "type": 1,
      "condition": 90,
      "name": "法术研习",
      "text": "请多加研习法术，让自己变得更强",
      "desc": "法术研习中",
      "doc": "法术已完成",
      "ress": {
        "10": 12
      },
      "weight": 1000,
      "time": 5
    },
    "1003": {
      "type": 1,
      "condition": 120,
      "name": "炼制圣药",
      "text": "请炼制超强圣药",
      "desc": "炼制圣药中",
      "doc": "炼制已完成",
      "ress": {
        "10": 16
      },
      "weight": 1000,
      "time": 6
    },
    "1004": {
      "type": 1,
      "condition": 150,
      "name": "采集药草",
      "text": "请出发前往采集炼制圣药的药草",
      "desc": "采集药草中",
      "doc": "采集已完成",
      "ress": {
        "10": 20
      },
      "weight": 1000,
      "time": 8
    },
    "1005": {
      "type": 1,
      "condition": 180,
      "name": "清理圣殿",
      "text": "圣殿脏了，请前往打扫",
      "desc": "清理圣殿中",
      "doc": "清理已完成",
      "ress": {
        "10": 24
      },
      "weight": 1000,
      "time": 9
    },
    "2001": {
      "type": 2,
      "condition": 90,
      "name": "调查坊市",
      "text": "坊市今日有黑商出没，速去查探",
      "desc": "正在调查黑商",
      "doc": "调查结束",
      "ress": {
        "10": 18
      },
      "weight": 500,
      "time": 5
    },
    "2002": {
      "type": 2,
      "condition": 120,
      "name": "聊天审查",
      "text": "聊天频道是我家，文明聊天靠大家",
      "desc": "正在审阅记录",
      "doc": "审查完毕",
      "ress": {
        "10": 24
      },
      "weight": 500,
      "time": 6
    },
    "2003": {
      "type": 2,
      "condition": 150,
      "name": "铁匠的委托",
      "text": "帮助铁匠，锻造绝世神器",
      "desc": "神器锻造中",
      "doc": "锻造完成",
      "ress": {
        "10": 30
      },
      "weight": 500,
      "time": 8
    },
    "2004": {
      "type": 2,
      "condition": 180,
      "name": "慰问云游商人",
      "text": "云游商人日夜操劳，回收装备，极需感情慰藉",
      "desc": "慰问商人中",
      "doc": "慰问结束",
      "ress": {
        "10": 36
      },
      "weight": 500,
      "time": 9
    },
    "2005": {
      "type": 2,
      "condition": 210,
      "name": "植被种植",
      "text": "王国西区的土地荒漠化，需要种植大量植被",
      "desc": "植被种植中",
      "doc": "种植完成",
      "ress": {
        "10": 42
      },
      "weight": 500,
      "time": 11
    },
    "3001": {
      "type": 3,
      "condition": 100,
      "name": "巫女的委托",
      "text": "帮助巫女修复魔法水晶球",
      "desc": "水晶球修复中",
      "doc": "修复完成",
      "ress": {
        "10": 27
      },
      "weight": 300,
      "time": 5
    },
    "3002": {
      "type": 3,
      "condition": 130,
      "name": "药店老板的委托",
      "text": "帮助药店老板去往洛托伊城购买药材",
      "desc": "购买药材中",
      "doc": "药材购买完毕",
      "ress": {
        "10": 35
      },
      "weight": 300,
      "time": 7
    },
    "3003": {
      "type": 3,
      "condition": 160,
      "name": "擦拭神兵",
      "text": "神兵久未开封，早已积灰",
      "desc": "正在擦拭神兵",
      "doc": "擦拭完成",
      "ress": {
        "10": 43
      },
      "weight": 300,
      "time": 8
    },
    "3004": {
      "type": 3,
      "condition": 190,
      "name": "调查黑市",
      "text": "据探子回报，有人通过黑市倒卖元宝，速去调查清楚",
      "desc": "正在黑市蹲守",
      "doc": "调查结束",
      "ress": {
        "10": 51
      },
      "weight": 300,
      "time": 10
    },
    "3005": {
      "type": 3,
      "condition": 220,
      "name": "丈量土地",
      "text": "王国领地扩张了，现需要重新统计",
      "desc": "丈量土地中",
      "doc": "土地丈量完成",
      "ress": {
        "10": 59
      },
      "weight": 300,
      "time": 11
    },
    "4001": {
      "type": 4,
      "condition": 120,
      "name": "照顾幼崽",
      "text": "白野猪外出了，现需要人手帮忙照顾白野猪的幼崽",
      "desc": "照顾幼崽中",
      "doc": "任务已完成",
      "ress": {
        "10": 40
      },
      "weight": 100,
      "time": 6
    },
    "4002": {
      "type": 4,
      "condition": 140,
      "name": "坊市调研",
      "text": "百姓投诉坊市的货物价格太高，速去调研所有货物价格",
      "desc": "坊市调研中",
      "doc": "价格调研完毕",
      "ress": {
        "10": 47
      },
      "weight": 100,
      "time": 7
    },
    "4003": {
      "type": 4,
      "condition": 160,
      "name": "修复烽火台",
      "text": "烽火台已经破旧不堪，不修复则无法使用",
      "desc": "正在修复中",
      "doc": "修复完成",
      "ress": {
        "10": 53
      },
      "weight": 100,
      "time": 8
    },
    "4004": {
      "type": 4,
      "condition": 180,
      "name": "剿灭海盗",
      "text": "外贸商船遭遇海盗，请前往支援",
      "desc": "正在剿灭海盗",
      "doc": "完成剿灭",
      "ress": {
        "10": 60
      },
      "weight": 100,
      "time": 9
    },
    "4005": {
      "type": 4,
      "condition": 220,
      "name": "采集矿石",
      "text": "矿脉采集人手不足，需要人手帮忙",
      "desc": "正在采集矿石",
      "doc": "采集完成",
      "ress": {
        "10": 73
      },
      "weight": 100,
      "time": 11
    },
    "5001": {
      "type": 5,
      "condition": 180,
      "name": "跑腿功夫",
      "text": "去东市帮我买个烧鹅腿吧",
      "desc": "正在配送",
      "doc": "跑腿已完成",
      "ress": {
        "10": 84
      },
      "award_item": {
        "I9161": 1
      },
      "weight": 50,
      "time": 9
    },
    "5002": {
      "type": 5,
      "condition": 220,
      "name": "贵族的委托",
      "text": "我心爱的小猫咪不见了，快去帮我找回来",
      "desc": "正在找寻小猫",
      "doc": "已找到小猫",
      "ress": {
        "10": 103
      },
      "award_item": {
        "I9161": 1
      },
      "weight": 50,
      "time": 11
    },
    "5003": {
      "type": 5,
      "condition": 260,
      "name": "祭奠英雄",
      "text": "英雄不可被遗忘，请前去祭奠",
      "desc": "祭奠英雄中",
      "doc": "祭奠完成",
      "ress": {
        "10": 121
      },
      "award_item": {
        "I9161": 1
      },
      "weight": 50,
      "time": 13
    },
    "5004": {
      "type": 5,
      "condition": 300,
      "name": "援助岛民",
      "text": "岛上遭遇海啸，速去前往救援",
      "desc": "人员搜救中",
      "doc": "搜救已完成",
      "ress": {
        "10": 140
      },
      "award_item": {
        "I9161": 1
      },
      "weight": 50,
      "time": 15
    },
    "5005": {
      "type": 5,
      "condition": 340,
      "name": "厨神大赛",
      "text": "参加厨神大赛展示厨艺",
      "desc": "烹饪中",
      "doc": "获得厨神称号",
      "ress": {
        "10": 159
      },
      "award_item": {
        "I9161": 1
      },
      "weight": 50,
      "time": 17
    },
    "6001": {
      "type": 6,
      "condition": 230,
      "name": "抓鬼驱邪",
      "text": "邻居新盖的府邸阴气萦绕，快去帮忙驱散邪灵",
      "desc": "法事进行中",
      "doc": "邪灵已退散",
      "ress": {
        "10": 138
      },
      "award_item": {
        "I9161": 2
      },
      "weight": 25,
      "time": 12
    },
    "6002": {
      "type": 6,
      "condition": 250,
      "name": "祭奠英雄",
      "text": "英雄不可被遗忘，请前去祭奠",
      "desc": "祭奠英雄中",
      "doc": "祭奠已完成",
      "ress": {
        "10": 150
      },
      "award_item": {
        "I9161": 2
      },
      "weight": 25,
      "time": 13
    },
    "6003": {
      "type": 6,
      "condition": 270,
      "name": "邪恶的炼金术士",
      "text": "城镇中出现了邪恶的炼金术士，请英雄们前往剿灭他们",
      "desc": "围剿中",
      "doc": "已全部剿灭",
      "ress": {
        "10": 162
      },
      "award_item": {
        "I9161": 2
      },
      "weight": 25,
      "time": 14
    },
    "6004": {
      "type": 6,
      "condition": 290,
      "name": "平定暴乱",
      "text": "镇子发生暴乱，百姓苦不堪言，剿灭暴徒，刻不容缓",
      "desc": "平定暴乱中",
      "doc": "暴乱已平",
      "ress": {
        "10": 174
      },
      "award_item": {
        "I9161": 2
      },
      "weight": 25,
      "time": 15
    },
    "6005": {
      "type": 6,
      "condition": 320,
      "name": "抓捕通缉犯",
      "text": "监狱里有个通缉犯逃跑了，速去抓捕回来",
      "desc": "正在抓捕中",
      "doc": "已抓住通缉犯",
      "ress": {
        "10": 192
      },
      "award_item": {
        "I9161": 2
      },
      "weight": 25,
      "time": 16
    },
    "7001": {
      "type": 7,
      "condition": 360,
      "name": "药王遗迹",
      "text": "千年前的药王留下来的遗迹现世了，速去探查一番",
      "desc": "正在探查中",
      "doc": "遗迹探查完毕",
      "ress": {
        "10": 264
      },
      "award_item": {
        "I9161": 4
      },
      "weight": 15,
      "time": 18
    },
    "7002": {
      "type": 7,
      "condition": 380,
      "name": "妖王现世",
      "text": "有妖王现世，正在祸害四方百姓，有能之士请前往灭杀",
      "desc": "正在灭杀妖王",
      "doc": "妖王已灭杀",
      "ress": {
        "10": 279
      },
      "award_item": {
        "I9161": 4
      },
      "weight": 15,
      "time": 19
    },
    "7003": {
      "type": 7,
      "condition": 400,
      "name": "王国密信",
      "text": "这是需要给邻国国主的信件，务必要让他亲自接收",
      "desc": "正在送信中",
      "doc": "信件已送达",
      "ress": {
        "10": 293
      },
      "award_item": {
        "I9161": 4
      },
      "weight": 15,
      "time": 20
    },
    "7004": {
      "type": 7,
      "condition": 420,
      "name": "接待神使",
      "text": "神明委派神使来王国抚恤百姓，现委派你去接待",
      "desc": "接待神使中",
      "doc": "神使已离去",
      "ress": {
        "10": 308
      },
      "award_item": {
        "I9161": 4
      },
      "weight": 15,
      "time": 21
    },
    "7005": {
      "type": 7,
      "condition": 440,
      "name": "神灵的贡品",
      "text": "给神灵的贡品不够了，麻烦去帮我们搜集更多的贡品",
      "desc": "寻找贡品中",
      "doc": "贡品数量够了",
      "ress": {
        "10": 323
      },
      "award_item": {
        "I9161": 4
      },
      "weight": 15,
      "time": 22
    },
    "8001": {
      "type": 8,
      "condition": 460,
      "name": "魔龙之祸",
      "text": "魔龙教主派手下攻打比奇城，损失惨重，速去协助作战",
      "desc": "正在抵御进攻",
      "doc": "击退魔龙战将",
      "ress": {
        "10": 399
      },
      "award_item": {
        "I9161": 8
      },
      "weight": 10,
      "time": 23
    },
    "8002": {
      "type": 8,
      "condition": 480,
      "name": "火龙神的邀请",
      "text": "龙神之子诞生，火龙神邀请前往参加庆祝宴",
      "desc": "正在庆祝中",
      "doc": "庆祝宴结束",
      "ress": {
        "10": 416
      },
      "award_item": {
        "I9161": 8
      },
      "weight": 10,
      "time": 24
    },
    "8003": {
      "type": 8,
      "condition": 500,
      "name": "雷炎主宰的挑衅",
      "text": "雷炎主宰挑衅王国，请前往雷炎国度杀杀它的嚣张气焰",
      "desc": "击败雷炎精英",
      "doc": "已击败对手",
      "ress": {
        "10": 433
      },
      "award_item": {
        "I9161": 8
      },
      "weight": 10,
      "time": 25
    },
    "8004": {
      "type": 8,
      "condition": 520,
      "name": "赤月的进攻",
      "text": "赤月恶魔发动战乱，无数百姓生活苦不堪言，速去协防",
      "desc": "击退恶魔中",
      "doc": "战争胜利",
      "ress": {
        "10": 451
      },
      "award_item": {
        "I9161": 8
      },
      "weight": 10,
      "time": 26
    },
    "8005": {
      "type": 8,
      "condition": 540,
      "name": "祖玛教主的仪式",
      "text": "祖玛教主正在举行邪恶的仪式，需要赶快阻止",
      "desc": "正在阻止仪式",
      "doc": "仪式举行失败",
      "ress": {
        "10": 468
      },
      "award_item": {
        "I9161": 8
      },
      "weight": 10,
      "time": 27
    }
  }
}