{
  "__type__": "cc.JsonAsset",
  "_name": "sevenDayLoginConfig",
  "json": {
    "1": {
      "day": 1,
      "ress": {
        "1": 5000,
        "2": 200
      },
      "item": {
        "I4001": 50,
        "I3004": 20,
        "I2101": 20
      }
    },
    "2": {
      "day": 2,
      "ress": {
        "1": 50000
      },
      "item": {
        "I4001": 50,
        "I3001": 50,
        "I2102": 20
      },
      "equip": {
        "D000009": 1
      }
    },
    "3": {
      "day": 3,
      "ress": {
        "1": 100000
      },
      "item": {
        "I3911": 1,
        "I3912": 1,
        "I3001": 50,
        "I3903": 50
      }
    },
    "4": {
      "day": 4,
      "ress": {
        "1": 100000,
        "2": 50
      },
      "item": {
        "I4008": 3,
        "I4001": 100,
        "I3004": 100
      }
    },
    "5": {
      "day": 5,
      "ress": {
        "1": 200000
      },
      "item": {
        "I8010": 1,
        "I7001": 5,
        "I7002": 3,
        "I7003": 1
      }
    },
    "6": {
      "day": 6,
      "ress": {
        "1": 200000
      },
      "item": {
        "I3133": 4,
        "I3905": 50,
        "I3906": 10,
        "I2103": 50
      }
    },
    "7": {
      "day": 7,
      "ress": {
        "1": 500000,
        "2": 100
      },
      "item": {
        "I7004": 1,
        "I3907": 50,
        "I3908": 10
      }
    }
  }
}