[
  {
    "__type__": "cc.SpriteFrame",
    "content": {
      "name": "img_ui_shuangdan_kuang",
      "texture": "1b95214d1",
      "rect": [
        935,
        908,
        113,
        78
      ],
      "offset": [
        0,
        0
      ],
      "originalSize": [
        113,
        78
      ],
      "rotated": 1,
      "capInsets": [
        35,
        21,
        25,
        23
      ]
    }
  },
  {
    "__type__": "cc.SpriteFrame",
    "content": {
      "name": "fontclib_zixuanlibao",
      "texture": "daGm4ahX9CppHjqAfLp4IU",
      "rect": [
        0,
        0,
        622,
        142
      ],
      "offset": [
        0,
        0
      ],
      "originalSize": [
        622,
        142
      ],
      "capInsets": [
        0,
        0,
        0,
        0
      ]
    }
  },
  [
    {
      "__type__": "cc.Prefab",
      "_name": "OptionalGiftBagView",
      "data": {
        "__id__": 1
      }
    },
    {
      "__type__": "cc.Node",
      "_name": "OptionalGiftBagView",
      "_children": [
        {
          "__id__": 2
        },
        {
          "__id__": 3
        }
      ],
      "_components": [
        {
          "__type__": "bdb1673/LhHsY1pyx6NCO8V",
          "node": {
            "__id__": 1
          },
          "itemPrefab": {
            "__uuid__": "30/teNtIpIoqmjEuuBzEoD"
          }
        }
      ],
      "_prefab": {
        "__type__": "cc.PrefabInfo",
        "root": {
          "__id__": 1
        },
        "asset": {
          "__uuid__": "d723o44pFMEq/Ed44NWVM4"
        },
        "fileId": "23CzgUZIBNZoSykQ6SRxQz"
      },
      "_contentSize": {
        "__type__": "cc.Size",
        "width": 640,
        "height": 1136
      },
      "_trs": {
        "__type__": "TypedArray",
        "ctor": "Float64Array",
        "array": [
          0,
          0,
          0,
          0,
          0,
          0,
          1,
          1,
          1,
          1
        ]
      }
    },
    {
      "__type__": "cc.Node",
      "_name": "darkLayer1",
      "_parent": {
        "__id__": 1
      },
      "_components": [
        {
          "__type__": "cc.Sprite",
          "node": {
            "__id__": 2
          },
          "_materials": [
            {
              "__uuid__": "ecpdLyjvZBwrvm+cedCcQy"
            }
          ],
          "_spriteFrame": {
            "__uuid__": "faGSEUALBDTZ4m77k/pLdP"
          },
          "_sizeMode": 0
        },
        {
          "__type__": "cc.Widget",
          "node": {
            "__id__": 2
          },
          "_alignFlags": 45,
          "_originalWidth": 100,
          "_originalHeight": 100
        },
        {
          "__type__": "cc.Button",
          "node": {
            "__id__": 2
          }
        }
      ],
      "_prefab": {
        "__type__": "cc.PrefabInfo",
        "root": {
          "__id__": 1
        },
        "asset": {
          "__uuid__": "d723o44pFMEq/Ed44NWVM4"
        },
        "fileId": "34wetYh8xLM6FmPTmB+BHa"
      },
      "_contentSize": {
        "__type__": "cc.Size",
        "width": 640,
        "height": 1136
      },
      "_position": {
        "__type__": "cc.Vec3"
      },
      "_scale": {
        "__type__": "cc.Vec3",
        "x": 1,
        "y": 1,
        "z": 1
      },
      "_trs": {
        "__type__": "TypedArray",
        "ctor": "Float64Array",
        "array": [
          0,
          0,
          0,
          0,
          0,
          0,
          1,
          1,
          1,
          1
        ]
      }
    },
    {
      "__type__": "cc.Node",
      "_name": "frame",
      "_parent": {
        "__id__": 1
      },
      "_children": [
        {
          "__id__": 4
        },
        {
          "__id__": 5
        },
        {
          "__id__": 7
        },
        {
          "__id__": 8
        }
      ],
      "_prefab": {
        "__type__": "cc.PrefabInfo",
        "root": {
          "__id__": 1
        },
        "asset": {
          "__uuid__": "d723o44pFMEq/Ed44NWVM4"
        },
        "fileId": "c6vc1z4u1OGYvDw0z9lugE"
      },
      "_contentSize": {
        "__type__": "cc.Size",
        "width": 640,
        "height": 784
      },
      "_trs": {
        "__type__": "TypedArray",
        "ctor": "Float64Array",
        "array": [
          0,
          -24,
          0,
          0,
          0,
          0,
          1,
          1,
          1,
          1
        ]
      }
    },
    {
      "__type__": "cc.Node",
      "_name": "top",
      "_parent": {
        "__id__": 3
      },
      "_components": [
        {
          "__type__": "cc.Sprite",
          "node": {
            "__id__": 4
          },
          "_materials": [
            {
              "__uuid__": "ecpdLyjvZBwrvm+cedCcQy"
            }
          ],
          "_spriteFrame": {
            "__uuid__": "7deokxyvhNdJZ9ZIuK8HHM"
          }
        }
      ],
      "_prefab": {
        "__type__": "cc.PrefabInfo",
        "root": {
          "__id__": 1
        },
        "asset": {
          "__uuid__": "d723o44pFMEq/Ed44NWVM4"
        },
        "fileId": "f0cJur+PhILZiNKYK525t9"
      },
      "_contentSize": {
        "__type__": "cc.Size",
        "width": 622,
        "height": 142
      },
      "_trs": {
        "__type__": "TypedArray",
        "ctor": "Float64Array",
        "array": [
          0,
          310,
          0,
          0,
          0,
          0,
          1,
          1,
          1,
          1
        ]
      }
    },
    {
      "__type__": "cc.Node",
      "_name": "avtivityTime",
      "_parent": {
        "__id__": 3
      },
      "_children": [
        {
          "__id__": 6
        }
      ],
      "_components": [
        {
          "__type__": "cc.Label",
          "node": {
            "__id__": 5
          },
          "_materials": [
            {
              "__uuid__": "ecpdLyjvZBwrvm+cedCcQy"
            }
          ],
          "_useOriginalSize": false,
          "_string": "活动剩余时间：",
          "_N$string": "活动剩余时间：",
          "_fontSize": 18,
          "_lineHeight": 18,
          "_N$horizontalAlign": 1,
          "_N$verticalAlign": 1,
          "_N$fontFamily": "SimHei"
        },
        {
          "__type__": "42c896PLUtB5a29kUw4vdKn",
          "node": {
            "__id__": 5
          },
          "code": 60790
        }
      ],
      "_prefab": {
        "__type__": "cc.PrefabInfo",
        "root": {
          "__id__": 1
        },
        "asset": {
          "__uuid__": "d723o44pFMEq/Ed44NWVM4"
        },
        "fileId": "a1MCcoC4VO66IQpBML0r3J"
      },
      "_color": {
        "__type__": "cc.Color",
        "r": 253,
        "g": 218,
        "b": 123
      },
      "_contentSize": {
        "__type__": "cc.Size",
        "width": 126,
        "height": 22.68
      },
      "_trs": {
        "__type__": "TypedArray",
        "ctor": "Float64Array",
        "array": [
          -120,
          223,
          0,
          0,
          0,
          0,
          1,
          1,
          1,
          1
        ]
      }
    },
    {
      "__type__": "cc.Node",
      "_name": "time",
      "_parent": {
        "__id__": 5
      },
      "_components": [
        {
          "__type__": "cc.Label",
          "node": {
            "__id__": 6
          },
          "_materials": [
            {
              "__uuid__": "ecpdLyjvZBwrvm+cedCcQy"
            }
          ],
          "_useOriginalSize": false,
          "_string": "2021年41月12日-2320年12月12日",
          "_N$string": "2021年41月12日-2320年12月12日",
          "_fontSize": 18,
          "_lineHeight": 18,
          "_N$horizontalAlign": 1,
          "_N$verticalAlign": 1,
          "_N$fontFamily": "SimHei"
        }
      ],
      "_prefab": {
        "__type__": "cc.PrefabInfo",
        "root": {
          "__id__": 1
        },
        "asset": {
          "__uuid__": "d723o44pFMEq/Ed44NWVM4"
        },
        "fileId": "c66+sCePROjpi4V5/ARUJ4"
      },
      "_contentSize": {
        "__type__": "cc.Size",
        "width": 261,
        "height": 22.68
      },
      "_anchorPoint": {
        "__type__": "cc.Vec2",
        "y": 0.5
      },
      "_trs": {
        "__type__": "TypedArray",
        "ctor": "Float64Array",
        "array": [
          63,
          0,
          0,
          0,
          0,
          0,
          1,
          1,
          1,
          1
        ]
      }
    },
    {
      "__type__": "cc.Node",
      "_name": "img_chegnzhangjijin_jiangli_bj",
      "_parent": {
        "__id__": 3
      },
      "_components": [
        {
          "__type__": "cc.Sprite",
          "node": {
            "__id__": 7
          },
          "_materials": [
            {
              "__uuid__": "ecpdLyjvZBwrvm+cedCcQy"
            }
          ],
          "_spriteFrame": {
            "__uuid__": "5fM2wTShpIUoLW36zrhZjq"
          },
          "_type": 1,
          "_sizeMode": 0
        }
      ],
      "_prefab": {
        "__type__": "cc.PrefabInfo",
        "root": {
          "__id__": 1
        },
        "asset": {
          "__uuid__": "d723o44pFMEq/Ed44NWVM4"
        },
        "fileId": "eafwagUhBElJEFJUzbes5b"
      },
      "_contentSize": {
        "__type__": "cc.Size",
        "width": 621,
        "height": 585
      },
      "_trs": {
        "__type__": "TypedArray",
        "ctor": "Float64Array",
        "array": [
          0,
          -88.938,
          0,
          0,
          0,
          0,
          1,
          1,
          1,
          1
        ]
      }
    },
    {
      "__type__": "cc.Node",
      "_name": "scrollView",
      "_parent": {
        "__id__": 3
      },
      "_children": [
        {
          "__id__": 9
        }
      ],
      "_components": [
        {
          "__type__": "cc.ScrollView",
          "node": {
            "__id__": 8
          },
          "horizontal": false,
          "_N$content": {
            "__id__": 10
          },
          "content": {
            "__id__": 10
          },
          "_N$horizontalScrollBar": null,
          "_N$verticalScrollBar": null
        }
      ],
      "_prefab": {
        "__type__": "cc.PrefabInfo",
        "root": {
          "__id__": 1
        },
        "asset": {
          "__uuid__": "d723o44pFMEq/Ed44NWVM4"
        },
        "fileId": "ab3dN+YvJKUp7H6BR1cke0"
      },
      "_contentSize": {
        "__type__": "cc.Size",
        "width": 621,
        "height": 575
      },
      "_anchorPoint": {
        "__type__": "cc.Vec2",
        "x": 0.5,
        "y": 1
      },
      "_trs": {
        "__type__": "TypedArray",
        "ctor": "Float64Array",
        "array": [
          0,
          198,
          0,
          0,
          0,
          0,
          1,
          1,
          1,
          1
        ]
      }
    },
    {
      "__type__": "cc.Node",
      "_name": "view",
      "_parent": {
        "__id__": 8
      },
      "_children": [
        {
          "__id__": 10
        }
      ],
      "_components": [
        {
          "__type__": "cc.Mask",
          "node": {
            "__id__": 9
          },
          "_materials": [
            {
              "__uuid__": "ecpdLyjvZBwrvm+cedCcQy"
            }
          ],
          "_N$alphaThreshold": 0
        }
      ],
      "_prefab": {
        "__type__": "cc.PrefabInfo",
        "root": {
          "__id__": 1
        },
        "asset": {
          "__uuid__": "d723o44pFMEq/Ed44NWVM4"
        },
        "fileId": "e8zI3FwahIHpCi5Kbrf6Y8"
      },
      "_contentSize": {
        "__type__": "cc.Size",
        "width": 621,
        "height": 575
      },
      "_anchorPoint": {
        "__type__": "cc.Vec2",
        "x": 0.5,
        "y": 1
      },
      "_trs": {
        "__type__": "TypedArray",
        "ctor": "Float64Array",
        "array": [
          0,
          0,
          0,
          0,
          0,
          0,
          1,
          1,
          1,
          1
        ]
      }
    },
    {
      "__type__": "cc.Node",
      "_name": "content",
      "_parent": {
        "__id__": 9
      },
      "_components": [
        {
          "__type__": "cc.Layout",
          "node": {
            "__id__": 10
          },
          "_layoutSize": {
            "__type__": "cc.Size",
            "width": 621,
            "height": 143
          },
          "_resize": 1,
          "_N$layoutType": 2,
          "_N$paddingTop": 7
        }
      ],
      "_prefab": {
        "__type__": "cc.PrefabInfo",
        "root": {
          "__id__": 1
        },
        "asset": {
          "__uuid__": "d723o44pFMEq/Ed44NWVM4"
        },
        "fileId": "73R7uoWV9IB5IGAGKHUzAi"
      },
      "_contentSize": {
        "__type__": "cc.Size",
        "width": 621,
        "height": 143
      },
      "_anchorPoint": {
        "__type__": "cc.Vec2",
        "x": 0.5,
        "y": 1
      },
      "_trs": {
        "__type__": "TypedArray",
        "ctor": "Float64Array",
        "array": [
          3,
          0,
          0,
          0,
          0,
          0,
          1,
          1,
          1,
          1
        ]
      }
    }
  ],
  {
    "__type__": "cc.SpriteFrame",
    "content": {
      "name": "back_01",
      "texture": "11dfc7ad0",
      "rect": [
        1013,
        643,
        6,
        6
      ],
      "offset": [
        0,
        0
      ],
      "originalSize": [
        6,
        6
      ],
      "capInsets": [
        0,
        0,
        0,
        0
      ]
    }
  }
]